Metadata-Version: 1.1
Name: redis-opentracing
Version: 1.0.0
Summary: OpenTracing support for Elasticsearch
Home-page: https://github.com/opentracing-contrib/python-redis/
Author: Carlos Alberto Cortez
Author-email: calberto.cortez@gmail.com
License: Apache License 2.0
Download-URL: https://github.com/opentracing-contrib/python-redis/tarball/1.0.0
